nerium/__init__.py
nerium/__version__.py
nerium/app.py
nerium/auth.py
nerium/commit.py
nerium/csv_result.py
nerium/data_source.py
nerium/db.py
nerium/discovery.py
nerium/formatter.py
nerium/query.py
nerium/streaming.py
nerium/utils.py
nerium/resultset/__init__.py
nerium/resultset/sql.py
nerium/schema/__init__.py
nerium/schema/compact.py
nerium/schema/default.py
Nerium-0.13.2.dist-info/LICENSE.md
Nerium-0.13.2.dist-info/METADATA
Nerium-0.13.2.dist-info/WHEEL
Nerium-0.13.2.dist-info/top_level.txt
Nerium-0.13.2.dist-info/RECORD
