Metadata-Version: 2.1
Name: Nerium
Version: 0.13.2
Summary: The little business intelligence engine that could.
Home-page: https://github.com/tym-xqo/nerium
Author: Thomas Yager-Madden
Author-email: yagermadden@gmail.com
License: Apache License, Version 2.0
Classifier: Development Status :: 5 - Production/Stable
Classifier: Environment :: Console
Classifier: Environment :: Web Environment
Classifier: License :: OSI Approved :: Apache Software License
Classifier: Operating System :: OS Independent
Classifier: Programming Language :: Python
Classifier: Programming Language :: Python :: 3
Classifier: Programming Language :: Python :: 3.6
Classifier: Programming Language :: Python :: 3.7
Classifier: Programming Language :: Python :: 3.8
Classifier: Programming Language :: Python :: 3.9
Classifier: Topic :: Database :: Front-Ends
Classifier: Topic :: Software Development :: Libraries
Classifier: Topic :: Utilities
Requires-Python: >=3.6.0
License-File: LICENSE.md
Requires-Dist: Flask
Requires-Dist: flask-cors
Requires-Dist: gitpython
Requires-Dist: marshmallow
Requires-Dist: pyyaml
Requires-Dist: requests
Requires-Dist: sqla-raw >=1.5.1
Requires-Dist: sqlparse
Requires-Dist: Werkzeug
Provides-Extra: mysql
Requires-Dist: PyMySQL ; extra == 'mysql'
Provides-Extra: pg
Requires-Dist: psycopg2 ; extra == 'pg'
